<?xml version="1.0" encoding="UTF-8"?>
<!DOCTYPE faces-config PUBLIC "-//Sun Microsystems, Inc.//DTD JavaServer Faces Config 1.1//EN"
                              "http://java.sun.com/dtd/web-facesconfig_1_1.dtd">
<faces-config>
    <managed-bean>
        <managed-bean-name>ApplicationBean1</managed-bean-name>
        <managed-bean-class>sip.ApplicationBean1</managed-bean-class>
        <managed-bean-scope>application</managed-bean-scope>
    </managed-bean>
    <managed-bean>
        <managed-bean-name>login</managed-bean-name>
        <managed-bean-class>sip.login</managed-bean-class>
        <managed-bean-scope>request</managed-bean-scope>
    </managed-bean>
    <managed-bean>
        <managed-bean-name>modulos$admin$tablas</managed-bean-name>
        <managed-bean-class>sip.modulos.admin.tablas</managed-bean-class>
        <managed-bean-scope>request</managed-bean-scope>
    </managed-bean>
    <managed-bean>
        <managed-bean-name>AdminSessionBean</managed-bean-name>
        <managed-bean-class>sip.AdminSessionBean</managed-bean-class>
        <managed-bean-scope>session</managed-bean-scope>
    </managed-bean>
    <managed-bean>
        <managed-bean-name>modulos$correspondencia$crear</managed-bean-name>
        <managed-bean-class>sip.modulos.correspondencia.crear</managed-bean-class>
        <managed-bean-scope>request</managed-bean-scope>
    </managed-bean>
    <managed-bean>
        <managed-bean-name>modulos$correspondencia$actualizar</managed-bean-name>
        <managed-bean-class>sip.modulos.correspondencia.actualizar</managed-bean-class>
        <managed-bean-scope>request</managed-bean-scope>
    </managed-bean>
    <managed-bean>
        <managed-bean-name>modulos$correspondencia$infodetallada</managed-bean-name>
        <managed-bean-class>sip.modulos.correspondencia.infodetallada</managed-bean-class>
        <managed-bean-scope>request</managed-bean-scope>
    </managed-bean>
    <managed-bean>
        <managed-bean-name>modulos$admin$personas</managed-bean-name>
        <managed-bean-class>sip.modulos.admin.personas</managed-bean-class>
        <managed-bean-scope>request</managed-bean-scope>
    </managed-bean>
    <managed-bean>
        <managed-bean-name>modulos$admin$recursos</managed-bean-name>
        <managed-bean-class>sip.modulos.admin.recursos</managed-bean-class>
        <managed-bean-scope>request</managed-bean-scope>
    </managed-bean>
    <managed-bean>
        <managed-bean-name>modulos$correspondencia$consultar</managed-bean-name>
        <managed-bean-class>sip.modulos.correspondencia.consultar</managed-bean-class>
        <managed-bean-scope>request</managed-bean-scope>
    </managed-bean>
    <managed-bean>
        <managed-bean-name>modulos$admin$roles</managed-bean-name>
        <managed-bean-class>sip.modulos.admin.roles</managed-bean-class>
        <managed-bean-scope>request</managed-bean-scope>
    </managed-bean>
    <managed-bean>
        <managed-bean-name>modulos$correspondencia$resbusqueda</managed-bean-name>
        <managed-bean-class>sip.modulos.correspondencia.resbusqueda</managed-bean-class>
        <managed-bean-scope>request</managed-bean-scope>
    </managed-bean>
    <managed-bean>
        <managed-bean-name>modulos$admin$roles</managed-bean-name>
        <managed-bean-class>sip.modulos.admin.roles</managed-bean-class>
        <managed-bean-scope>request</managed-bean-scope>
    </managed-bean>
    <managed-bean>
        <managed-bean-name>modulos$admin$usuarios</managed-bean-name>
        <managed-bean-class>sip.modulos.admin.usuarios</managed-bean-class>
        <managed-bean-scope>request</managed-bean-scope>
    </managed-bean>
    <managed-bean>
        <managed-bean-name>modulos$admin$perfiles</managed-bean-name>
        <managed-bean-class>sip.modulos.admin.perfiles</managed-bean-class>
        <managed-bean-scope>request</managed-bean-scope>
    </managed-bean>
    <managed-bean>
        <managed-bean-name>modulos$admin$permisos</managed-bean-name>
        <managed-bean-class>sip.modulos.admin.permisos</managed-bean-class>
        <managed-bean-scope>request</managed-bean-scope>
    </managed-bean>
    <managed-bean>
        <managed-bean-name>CorrespondenciaSessionBean</managed-bean-name>
        <managed-bean-class>sip.CorrespondenciaSessionBean</managed-bean-class>
        <managed-bean-scope>session</managed-bean-scope>
    </managed-bean>
    <managed-bean>
        <managed-bean-name>modulos$auditoria$logConsultaForm</managed-bean-name>
        <managed-bean-class>sip.modulos.auditoria.logConsultaForm</managed-bean-class>
        <managed-bean-scope>request</managed-bean-scope>
    </managed-bean>
    <managed-bean>
        <managed-bean-name>modulos$auditoria$logList</managed-bean-name>
        <managed-bean-class>sip.modulos.auditoria.logList</managed-bean-class>
        <managed-bean-scope>request</managed-bean-scope>
    </managed-bean>
    <managed-bean>
        <managed-bean-name>ayuda</managed-bean-name>
        <managed-bean-class>sip.ayuda</managed-bean-class>
        <managed-bean-scope>request</managed-bean-scope>
    </managed-bean>
    <managed-bean>
        <managed-bean-name>modulos$correspondencia$download</managed-bean-name>
        <managed-bean-class>sip.modulos.correspondencia.download</managed-bean-class>
        <managed-bean-scope>request</managed-bean-scope>
    </managed-bean>
    <managed-bean>
        <managed-bean-name>modulos$correspondencia$sendMail</managed-bean-name>
        <managed-bean-class>sip.modulos.correspondencia.sendMail</managed-bean-class>
        <managed-bean-scope>request</managed-bean-scope>
    </managed-bean>
    <managed-bean>
        <managed-bean-name>modulos$common$buscarPersona</managed-bean-name>
        <managed-bean-class>sip.modulos.common.buscarPersona</managed-bean-class>
        <managed-bean-scope>request</managed-bean-scope>
    </managed-bean>
    <managed-bean>
        <managed-bean-name>UserInfoSessionBean</managed-bean-name>
        <managed-bean-class>sip.UserInfoSessionBean</managed-bean-class>
        <managed-bean-scope>session</managed-bean-scope>
    </managed-bean>
    <managed-bean>
        <managed-bean-name>noautorizado</managed-bean-name>
        <managed-bean-class>sip.noautorizado</managed-bean-class>
        <managed-bean-scope>request</managed-bean-scope>
    </managed-bean>
    <managed-bean>
        <managed-bean-name>menu</managed-bean-name>
        <managed-bean-class>sip.menu</managed-bean-class>
        <managed-bean-scope>request</managed-bean-scope>
    </managed-bean>
    <managed-bean>
        <managed-bean-name>main</managed-bean-name>
        <managed-bean-class>sip.main</managed-bean-class>
        <managed-bean-scope>request</managed-bean-scope>
    </managed-bean>
    <managed-bean>
        <managed-bean-name>logout</managed-bean-name>
        <managed-bean-class>sip.logout</managed-bean-class>
        <managed-bean-scope>request</managed-bean-scope>
    </managed-bean>
    <managed-bean>
        <managed-bean-name>footer</managed-bean-name>
        <managed-bean-class>sip.footer</managed-bean-class>
        <managed-bean-scope>request</managed-bean-scope>
    </managed-bean>
    <managed-bean>
        <managed-bean-name>_header</managed-bean-name>
        <managed-bean-class>sip.header</managed-bean-class>
        <managed-bean-scope>request</managed-bean-scope>
    </managed-bean>
    <managed-bean>
        <managed-bean-name>modulos$ayuda$general</managed-bean-name>
        <managed-bean-class>sip.modulos.ayuda.general</managed-bean-class>
        <managed-bean-scope>request</managed-bean-scope>
    </managed-bean>
    <managed-bean>
        <managed-bean-name>modulos$ayuda$admin</managed-bean-name>
        <managed-bean-class>sip.modulos.ayuda.admin</managed-bean-class>
        <managed-bean-scope>request</managed-bean-scope>
    </managed-bean>
    <managed-bean>
        <managed-bean-name>modulos$ayuda$correspondencia</managed-bean-name>
        <managed-bean-class>sip.modulos.ayuda.correspondencia</managed-bean-class>
        <managed-bean-scope>request</managed-bean-scope>
    </managed-bean>
</faces-config>
